MeteorologicalToolkit/__init__.py
MeteorologicalToolkit/test.py
MeteorologicalToolkit/interpolate/__init__.py
MeteorologicalToolkit/interpolate/grid2grid.py
MeteorologicalToolkit/interpolate/point2grid.py
MeteorologicalToolkit/panel/__init__.py
MeteorologicalToolkit/panel/add.py
MeteorologicalToolkit/panel/init.py
MeteorologicalToolkit/panel/plot.py
MeteorologicalToolkit/panel/select.py
MeteorologicalToolkit/panel/set.py
MeteorologicalToolkit/panel/smooth.py
MeteorologicalToolkit/panel/test.py
MeteorologicalToolkit/strategy/__init__.py
MeteorologicalToolkit/strategy/convert.py
MeteorologicalToolkit/strategy/generate.py
MeteorologicalToolkit-0.9.dist-info/METADATA
MeteorologicalToolkit-0.9.dist-info/WHEEL
MeteorologicalToolkit-0.9.dist-info/top_level.txt
MeteorologicalToolkit-0.9.dist-info/RECORD
